{
  "Categories": [
    {
      "Name": "arhitektura",
      "Id": 303
    },
    {
      "Name": "automobili",
      "Id": 304
    },
    {
      "Name": "biologija",
      "Id": 305
    },
    {
      "Name": "botanika",
      "Id": 306
    },
    {
      "Name": "brojevi",
      "Id": 307
    },
    {
      "Name": "cestice",
      "Id": 308
    },
    {
      "Name": "dijalekt",
      "Id": 309
    },
    {
      "Name": "ekonomija",
      "Id": 310
    },
    {
      "Name": "enigmatskispecijaliteti",
      "Id": 311
    },
    {
      "Name": "filozofija",
      "Id": 312
    },
    {
      "Name": "fizika",
      "Id": 313
    },
    {
      "Name": "fotografija",
      "Id": 314
    },
    {
      "Name": "gastronomija",
      "Id": 315
    },
    {
      "Name": "glagoli",
      "Id": 316
    },
    {
      "Name": "gramatika",
      "Id": 317
    },
    {
      "Name": "imena",
      "Id": 318
    },
    {
      "Name": "imenice",
      "Id": 319
    },
    {
      "Name": "it",
      "Id": 320
    },
    {
      "Name": "kemija",
      "Id": 321
    },
    {
      "Name": "kiparstvo",
      "Id": 322
    },
    {
      "Name": "kratice",
      "Id": 323
    },
    {
      "Name": "kultura",
      "Id": 324
    },
    {
      "Name": "matematika",
      "Id": 325
    },
    {
      "Name": "medicina",
      "Id": 326
    },
    {
      "Name": "mitologija",
      "Id": 327
    },
    {
      "Name": "moda",
      "Id": 328
    },
    {
      "Name": "nerazvrstano",
      "Id": 329
    },
    {
      "Name": "opcipojmovi",
      "Id": 330
    },
    {
      "Name": "politika",
      "Id": 331
    },
    {
      "Name": "poslovice",
      "Id": 332
    },
    {
      "Name": "povijest",
      "Id": 333
    },
    {
      "Name": "prenesnoznacenje",
      "Id": 334
    },
    {
      "Name": "pridjevi",
      "Id": 335
    },
    {
      "Name": "prijedlozi",
      "Id": 336
    },
    {
      "Name": "prilozi_ci",
      "Id": 337
    },
    {
      "Name": "sport",
      "Id": 338
    },
    {
      "Name": "stranerijeci",
      "Id": 339
    },
    {
      "Name": "umanjenice",
      "Id": 340
    },
    {
      "Name": "umjetnost",
      "Id": 341
    },
    {
      "Name": "uzvici",
      "Id": 342
    },
    {
      "Name": "veznici",
      "Id": 343
    },
    {
      "Name": "zamjenice",
      "Id": 344
    },
    {
      "Name": "zemljopis",
      "Id": 345
    },
    {
      "Name": "zoologija",
      "Id": 346
    }
  ]
}