[
  { "o": "Odjeća spremna za nošenje", "w": "PRET-A-PORTER" },
  { "o": "Moda nadahnuta prošlošću", "w": "RETRO STIL" },
  { "o": "Odjeća iz drugog razdoblja", "w": "VINTAGE" },
  { "o": "Prva linija modela na reviji", "w": "AVANTGARDA" },
  { "o": "Umjetno krzno ili koža", "w": "EKO KOŽA" },
  { "o": "Vrsta fine vunene tkanine", "w": "KAŠMIR" },
  { "o": "Gruba vunena tkanina s uzorkom", "w": "TVID" },
  { "o": "Kroj koji prati liniju tijela", "w": "SLIM FIT" },
  { "o": "Kratka ženska suknja", "w": "MINI SUKNJA" },
  { "o": "Gornji dio odjeće bez rukava", "w": "PRSLUK" },
  { "o": "Jednodijelni odjevni predmet", "w": "KOMBINEZON" },

  { "o": "Vrsta sjajne i glatke tkanine", "w": "SATEN" },
  { "o": "Baršunasta tkanina s rebrima", "w": "SAMOT" },
  { "o": "Lagana pamučna tkanina", "w": "MUSLIN" },
  { "o": "Prozračna mrežasta tkanina", "w": "TIL" },
  { "o": "Krojački nabor na tkanini", "w": "PLISE" },
  { "o": "Duboki izrez na odjeći", "w": "DEKOLTE" },
  { "o": "Visoka potpetica na cipeli", "w": "ŠTIKLA" },
  { "o": "Cipele s punim potplatom", "w": "PLATFORME" },
  { "o": "Mekana koža s dlačicama", "w": "BRUŠENA KOŽA" },
  { "o": "Karirani uzorak škotskog podrijetla", "w": "TARTAN" },
  { "o": "Traper hlače s tregerima", "w": "TREGERICE" },
  { "o": "Majica s visokim ovratnikom", "w": "DOLČEVITA" },
  { "o": "Široki kožni ili tekstilni obruč", "w": "REMEN" },
  { "o": "Modni ukras na reveru", "w": "BROŠ" },
  { "o": "Dugačka ženska haljina", "w": "MAKSI HALJINA" },
  { "o": "Kratka jakna do struka", "w": "BOLERO" },
  { "o": "Osoba koja nosi modele", "w": "MANEKEN" },
  { "o": "Osoba koja nosi modele", "w": "MANEKENKA" },
  { "o": "Vrhunac modne sezone", "w": "TREND" },

  { "o": "Gornji dio odjeće bez rukava (mn.)", "w": "PRSLUCI" },
  { "o": "Jednodijelni odjevni predmet (mn.)", "w": "KOMBINEZONI" },
  { "o": "Visoka potpetica na cipeli (mn.)", "w": "ŠTIKLE" },
  { "o": "Cipele s punim potplatom (mn.)", "w": "PLATFORME" },
  { "o": "Mekana koža s dlačicama (mn.)", "w": "BRUŠENE KOŽE" },
  { "o": "Traper hlače s tregerima (mn.)", "w": "TREGERICE" },
  { "o": "Majica s visokim ovratnikom (mn.)", "w": "DOLČEVITE" },
  { "o": "Široki kožni ili tekstilni obruč (mn.)", "w": "REMENI" },
  { "o": "Modni ukras na reveru (mn.)", "w": "BROŠEVI" },
  { "o": "Dugačka ženska haljina (mn.)", "w": "MAKSI HALJINE" },
  { "o": "Kratka jakna do struka (mn.)", "w": "BOLERA" },
  { "o": "Osoba koja nosi modele (mn.)", "w": "MANEKENI" },
  { "o": "Osoba koja nosi modele (mn.)", "w": "MANEKENKE" },
  { "o": "Vrhunac modne sezone (mn.)", "w": "TRENDOVI" },

  { "o": "Osnivačica modne kuće Chanel", "w": "COCO CHANEL" },
  { "o": "Kreator 'New Look' siluete", "w": "CHRISTIAN DIOR" },
  { "o": "Talijanski majstor odijela", "w": "GIORGIO ARMANI" },
  { "o": "Majstor visoke mode iz Španjolske", "w": "CRISTOBAL BALENCIAGA" },
  { "o": "Autor ženskog smokinga", "w": "YVES SAINT LAURENT" },
  { "o": "Autorica haljine na preklop", "w": "DIANE VON FURSTENBERG" },
  { "o": "Osnivač kuće Gucci", "w": "GUCCIO GUCCI" },
  { "o": "Kreativni genij kuće Chanel", "w": "KARL LAGERFELD" },
  { "o": "Kralj raskošne crvene boje", "w": "VALENTINO GARAVANI" },
  { "o": "Ekstravagantni osnivač Versacea", "w": "GIANNI VERSACE" },
  { "o": "Sestra Giannija i ikona brenda", "w": "DONATELLA VERSACE" },
  { "o": "Majstor mračnog glamura", "w": "ALEXANDER MCQUEEN" },
  { "o": "Britanska kraljica punk mode", "w": "VIVIENNE WESTWOOD" },
  { "o": "Dizajnerica slavnih vjenčanica", "w": "VERA WANG" },
  { "o": "Pionirka modernog minimalizma", "w": "JIL SANDER" },
  { "o": "Spojio sport i luksuz", "w": "RALPH LAUREN" },
  { "o": "Američki majstor minimalizma", "w": "CALVIN KLEIN" },
  { "o": "Bivši direktor Guccija", "w": "TOM FORD" },
  { "o": "Proslavila najlon u modi", "w": "MIUCCIA PRADA" },
  { "o": "Japanski majstor nabora", "w": "ISSEY MIYAKE" },
  { "o": "Osnivačica Comme des Garçons", "w": "REI KAWAKUBO" },
  { "o": "Majstor avangardnih krojeva", "w": "YOHJI YAMAMOTO" },
  { "o": "Kralj američke ležernosti", "w": "MICHAEL KORS" },
  { "o": "Francuski dizajner na pruge", "w": "JEAN PAUL GAULTIER" },
  { "o": "Cipele s crvenim potplatom", "w": "CHRISTIAN LOUBOUTIN" },
  { "o": "Majstor cipela iz serije", "w": "MANOLO BLAHNIK" },
  { "o": "Osnivač kuće luksuznih torbi", "w": "LOUIS VUITTON" },
  { "o": "Dizajner boemskog stila", "w": "OSCAR DE LA RENTA" },
  { "o": "Majstor futurističke mode", "w": "PIERRE CARDIN" },
  { "o": "Stvorio stil Audrey Hepburn", "w": "HUBERT DE GIVENCHY" },
  { "o": "Dizajnerica pletenine i pruga", "w": "SONIA RYKIEL" },
  { "o": "Britanska dizajnerica i pjevačica", "w": "VICTORIA BECKHAM" },
  { "o": "Dizajnerica održive mode", "w": "STELLA MCCARTNEY" },
  { "o": "Osnivač brenda Off-White", "w": "VIRGIL ABLOH" },
  { "o": "Stvorio 'Space Age' stil", "w": "ANDRE COURREGES" },
  { "o": "Autor metalnih haljina", "w": "PACO RABANNE" },
  { "o": "Osnivačica kuće Fendi", "w": "ADELE FENDI" },
  { "o": "Bivši kreativni direktor Diora", "w": "RAF SIMONS" },
  { "o": "Majstor romantičnog dizajna", "w": "JOHN GALLIANO" },
  { "o": "Dizajnerica šarenog kolorita", "w": "ROSITA MISSONI" },
  { "o": "Poznati dizajner cipela", "w": "JIMMY CHOO" },
  { "o": "Dizajner žarkih boja i printa", "w": "EMILIO PUCCI" },
  { "o": "Francuski modni inovator", "w": "THIERRY MUGLER" },
  { "o": "Dizajner pletenih torbi", "w": "BOTTEGA VENETA" },
  { "o": "Kreator 'prep' stila", "w": "TOMMY HILFIGER" },
  { "o": "Uvela eleganciju u sport", "w": "DONNA KARAN" },
  { "o": "Osnivač kuće Kenzo", "w": "KENZO TAKADA" },
  { "o": "Autor avangardnih cipela", "w": "RICK OWENS" },
  { "o": "Dizajnerica torbi i dodataka", "w": "KATE SPADE" },
  { "o": "Dizajner šarenih pruga", "w": "PAUL SMITH" },

  { "o": "Coco, osnivačica kuće Chanel", "w": "CHANEL" },
  { "o": "Christian, kreator 'New Looka'", "w": "DIOR" },
  { "o": "Giorgio, talijanski majstor", "w": "ARMANI" },
  { "o": "Cristobal, majstor visoke mode", "w": "BALENCIIAGA" },
  { "o": "Yves, autor ženskog smokinga", "w": "SAINT LAURENT" },
  { "o": "Diane, autorica haljine na preklop", "w": "VON FURSTENBERG" },
  { "o": "Guccio, osnivač kuće", "w": "GUCCI" },
  { "o": "Karl, kreativni genij Chanela", "w": "LAGERFELD" },
  { "o": "Valentino, kralj crvene boje", "w": "GARAVANI" },
  { "o": "Gianni, osnivač Versacea", "w": "VERSACE" },
  { "o": "Donatella, ikona brenda", "w": "VERSACE" },
  { "o": "Alexander, majstor mračnog glama", "w": "MCQUEEN" },
  { "o": "Vivienne, kraljica punk mode", "w": "WESTWOOD" },
  { "o": "Vera, dizajnerica vjenčanica", "w": "WANG" },
  { "o": "Jil, pionirka minimalizma", "w": "SANDER" },
  { "o": "Ralph, spojio sport i luksuz", "w": "LAUREN" },
  { "o": "Calvin, majstor minimalizma", "w": "KLEIN" },
  { "o": "Tom, bivši direktor Guccija", "w": "FORD" },
  { "o": "Miuccia, proslavila najlon", "w": "PRADA" },
  { "o": "Issey, japanski majstor nabora", "w": "MIYAKE" },
  { "o": "Rei, osnivačica Comme des Garçons", "w": "KAWAKUBO" },
  { "o": "Yohji, majstor avangarde", "w": "YAMAMOTO" },
  { "o": "Michael, kralj ležernosti", "w": "KORS" },
  { "o": "Jean Paul, dizajner na pruge", "w": "GAULTIER" },
  { "o": "Christian, crveni potplat", "w": "LOUBOUTIN" },
  { "o": "Manolo, majstor cipela", "w": "BLAHNIK" },
  { "o": "Louis, osnivač kuće torbi", "w": "VUITTON" },
  { "o": "Oscar, boemski stil", "w": "DE LA RENTA" },
  { "o": "Pierre, majstor futurizma", "w": "CARDIN" },
  { "o": "Hubert, stil Audrey Hepburn", "w": "GIVENCHY" },
  { "o": "Sonia, pletenina i pruge", "w": "RYKIEL" },
  { "o": "Victoria, dizajnerica i pjevačica", "w": "BECKHAM" },
  { "o": "Stella, održiva moda", "w": "MCCARTNEY" },
  { "o": "Virgil, osnivač Off-Whitea", "w": "ABLOH" },
  { "o": "Andre, 'Space Age' stil", "w": "COURREGES" },
  { "o": "Paco, metalne haljine", "w": "RABANNE" },
  { "o": "Adele, osnivačica kuće Fendi", "w": "FENDI" },
  { "o": "Raf, bivši direktor Diora", "w": "SIMONS" },
  { "o": "John, romantični dizajn", "w": "GALLIANO" },
  { "o": "Rosita, šareni kolorit", "w": "MISSONI" },
  { "o": "Jimmy, poznati dizajner cipela", "w": "CHOO" },
  { "o": "Emilio, žarke boje i print", "w": "PUCCI" },
  { "o": "Thierry, modni inovator", "w": "MUGLER" },
  { "o": "Bottega Veneta, pletene torbe", "w": "VENETA" },
  { "o": "Tommy, kreator 'prep' stila", "w": "HILFIGER" },
  { "o": "Donna, elegancija u sportu", "w": "KARAN" },
  { "o": "Kenzo, osnivač kuće", "w": "TAKADA" },
  { "o": "Rick, avangardne cipele", "w": "OWENS" },
  { "o": "Kate, torbe i dodaci", "w": "SPADE" },
  { "o": "Paul, šarene pruge", "w": "SMITH" },

  { "o": "Chanel, osnivačica modne kuće", "w": "COCO" },
  { "o": "Dior, kreator 'New Looka'", "w": "CHRISTIAN" },
  { "o": "Armani, talijanski majstor", "w": "GIORGIO" },
  { "o": "Balenciaga, majstor visoke mode", "w": "CRISTOBAL" },
  { "o": "St. Laurent, ženski smoking", "w": "YVES" },
  { "o": "Furstenberg, haljina na preklop", "w": "DIANE" },
  { "o": "Gucci, osnivač luksuzne kuće", "w": "GUCCIO" },
  { "o": "Lagerfeld, genij Chanela", "w": "KARL" },
  { "o": "Garavani, kralj crvene boje", "w": "VALENTINO" },
  { "o": "Versace, osnivač carstva", "w": "GIANNI" },
  { "o": "Versace, ikona i sestra osnivača", "w": "DONATELLA" },
  { "o": "McQueen, mračni glamur", "w": "ALEXANDER" },
  { "o": "Westwood, kraljica punka", "w": "VIVIENNE" },
  { "o": "Wang, dizajnerica vjenčanica", "w": "VERA" },
  { "o": "Sander, pionirka minimalizma", "w": "JIL" },
  { "o": "Lauren, sport i luksuz", "w": "RALPH" },
  { "o": "Klein, majstor minimalizma", "w": "CALVIN" },
  { "o": "Ford, bivši direktor Guccija", "w": "TOM" },
  { "o": "Prada, proslavila najlon", "w": "MIUCCIA" },
  { "o": "Miyake, japanski majstor nabora", "w": "ISSEY" },
  { "o": "Kawakubo, osn. Comme des Garçons", "w": "REI" },
  { "o": "Yamamoto, majstor avangarde", "w": "YOHJI" },
  { "o": "Kors, kralj am. ležernosti", "w": "MICHAEL" },
  { "o": "Gaultier, dizajner na pruge", "w": "JEAN PAUL" },
  { "o": "Louboutin, crveni potplati", "w": "CHRISTIAN" },
  { "o": "Blahnik, majstor cipela", "w": "MANOLO" },
  { "o": "Vuitton, osnivač kuće torbi", "w": "LOUIS" },
  { "o": "De la Renta, boemski stil", "w": "OSCAR" },
  { "o": "Cardin, futuristička moda", "w": "PIERRE" },
  { "o": "Givenchy, stil Audrey Hepburn", "w": "HUBERT" },
  { "o": "Rykiel, pletenina i pruge", "w": "SONIA" },
  { "o": "Beckham, dizajnerica i pjevačica", "w": "VICTORIA" },
  { "o": "McCartney, održiva moda", "w": "STELLA" },
  { "o": "Abloh, osnivač Off-Whitea", "w": "VIRGIL" },
  { "o": "Courreges, 'Space Age' stil", "w": "ANDRE" },
  { "o": "Rabanne, metalne haljine", "w": "PACO" },
  { "o": "Fendi, osnivačica kuće", "w": "ADELE" },
  { "o": "Simons, bivši direktor Diora", "w": "RAF" },
  { "o": "Galliano, romantični dizajn", "w": "JOHN" },
  { "o": "Missoni, šareni kolorit", "w": "ROSITA" },
  { "o": "Choo, poznati dizajner cipela", "w": "JIMMY" },
  { "o": "Pucci, žarke boje i print", "w": "EMILIO" },
  { "o": "Mugler, modni inovator", "w": "THIERRY" },
  { "o": "Veneta, pletene torbe", "w": "BOTTEGA" },
  { "o": "Hilfiger, kreator 'prep' stila", "w": "TOMMY" },
  { "o": "Karan, elegancija u sportu", "w": "DONNA" },
  { "o": "Takada, osnivač kuće Kenzo", "w": "KENZO" },
  { "o": "Owens, avangardne cipele", "w": "RICK" },
  { "o": "Spade, torbe i dodaci", "w": "KATE" },
  { "o": "Smith, šarene pruge", "w": "PAUL" }
]
