{
  "TemplateId": 11,
  "IsSolved": true,
  "State": {
    "AssignedTermsBySlotId": {
      "8": {
        "SlotId": 8,
        "TermId": 138971,
        "Letters": [
          "T",
          "O",
          "R",
          "O",
          "N",
          "T",
          "O"
        ]
      },
      "4": {
        "SlotId": 4,
        "TermId": 307501,
        "Letters": [
          "O",
          "T",
          "T",
          "A",
          "W",
          "A"
        ]
      },
      "38": {
        "SlotId": 38,
        "TermId": 88397,
        "Letters": [
          "L",
          "A",
          "W",
          "S",
          "O",
          "N"
        ]
      },
      "21": {
        "SlotId": 21,
        "TermId": 6391,
        "Letters": [
          "A",
          "O"
        ]
      },
      "17": {
        "SlotId": 17,
        "TermId": 7262,
        "Letters": [
          "A"
        ]
      },
      "2": {
        "SlotId": 2,
        "TermId": 7815,
        "Letters": [
          "I"
        ]
      },
      "7": {
        "SlotId": 7,
        "TermId": 7762,
        "Letters": [
          "A"
        ]
      },
      "9": {
        "SlotId": 9,
        "TermId": 6988,
        "Letters": [
          "R"
        ]
      },
      "18": {
        "SlotId": 18,
        "TermId": 7766,
        "Letters": [
          "A"
        ]
      },
      "24": {
        "SlotId": 24,
        "TermId": 7770,
        "Letters": [
          "A"
        ]
      },
      "32": {
        "SlotId": 32,
        "TermId": 7270,
        "Letters": [
          "N"
        ]
      },
      "44": {
        "SlotId": 44,
        "TermId": 3362,
        "Letters": [
          "C"
        ]
      },
      "39": {
        "SlotId": 39,
        "TermId": 5965,
        "Letters": [
          "C",
          "A"
        ]
      },
      "49": {
        "SlotId": 49,
        "TermId": 7774,
        "Letters": [
          "A"
        ]
      },
      "67": {
        "SlotId": 67,
        "TermId": 150632,
        "Letters": [
          "A"
        ]
      },
      "68": {
        "SlotId": 68,
        "TermId": 150751,
        "Letters": [
          "A"
        ]
      },
      "73": {
        "SlotId": 73,
        "TermId": 150805,
        "Letters": [
          "A"
        ]
      },
      "86": {
        "SlotId": 86,
        "TermId": 150812,
        "Letters": [
          "A"
        ]
      },
      "88": {
        "SlotId": 88,
        "TermId": 150820,
        "Letters": [
          "A"
        ]
      },
      "99": {
        "SlotId": 99,
        "TermId": 306940,
        "Letters": [
          "A"
        ]
      },
      "109": {
        "SlotId": 109,
        "TermId": 307043,
        "Letters": [
          "A"
        ]
      },
      "113": {
        "SlotId": 113,
        "TermId": 6957,
        "Letters": [
          "C"
        ]
      },
      "116": {
        "SlotId": 116,
        "TermId": 7273,
        "Letters": [
          "C"
        ]
      },
      "122": {
        "SlotId": 122,
        "TermId": 8025,
        "Letters": [
          "C",
          "A"
        ]
      },
      "118": {
        "SlotId": 118,
        "TermId": 6990,
        "Letters": [
          "S"
        ]
      },
      "120": {
        "SlotId": 120,
        "TermId": 7817,
        "Letters": [
          "I"
        ]
      },
      "28": {
        "SlotId": 28,
        "TermId": 26017,
        "Letters": [
          "R",
          "A",
          "N",
          "I"
        ]
      },
      "13": {
        "SlotId": 13,
        "TermId": 94454,
        "Letters": [
          "M",
          "I",
          "M",
          "O"
        ]
      },
      "3": {
        "SlotId": 3,
        "TermId": 7192,
        "Letters": [
          "M",
          "S"
        ]
      },
      "1": {
        "SlotId": 1,
        "TermId": 90769,
        "Letters": [
          "M",
          "A",
          "C",
          "K"
        ]
      },
      "25": {
        "SlotId": 25,
        "TermId": 8471,
        "Letters": [
          "C",
          "A"
        ]
      },
      "20": {
        "SlotId": 20,
        "TermId": 150962,
        "Letters": [
          "A",
          "A",
          "L"
        ]
      },
      "31": {
        "SlotId": 31,
        "TermId": 79679,
        "Letters": [
          "K",
          "A",
          "N",
          "A"
        ]
      },
      "35": {
        "SlotId": 35,
        "TermId": 102231,
        "Letters": [
          "N",
          "S",
          "A"
        ]
      },
      "40": {
        "SlotId": 40,
        "TermId": 151103,
        "Letters": [
          "A",
          "N",
          "S"
        ]
      },
      "19": {
        "SlotId": 19,
        "TermId": 132219,
        "Letters": [
          "S",
          "T",
          "A",
          "R",
          "A"
        ]
      },
      "15": {
        "SlotId": 15,
        "TermId": 5968,
        "Letters": [
          "A",
          "R"
        ]
      },
      "5": {
        "SlotId": 5,
        "TermId": 157768,
        "Letters": [
          "A",
          "R",
          "I",
          "N",
          "O"
        ]
      },
      "26": {
        "SlotId": 26,
        "TermId": 139877,
        "Letters": [
          "T",
          "R",
          "I",
          "K",
          "I"
        ]
      },
      "6": {
        "SlotId": 6,
        "TermId": 150961,
        "Letters": [
          "A",
          "A",
          "K"
        ]
      },
      "14": {
        "SlotId": 14,
        "TermId": 150888,
        "Letters": [
          "A",
          "A",
          "A"
        ]
      },
      "22": {
        "SlotId": 22,
        "TermId": 8936,
        "Letters": [
          "I",
          "A"
        ]
      },
      "34": {
        "SlotId": 34,
        "TermId": 150966,
        "Letters": [
          "A",
          "A",
          "O"
        ]
      },
      "29": {
        "SlotId": 29,
        "TermId": 6757,
        "Letters": [
          "A",
          "A",
          "E"
        ]
      },
      "47": {
        "SlotId": 47,
        "TermId": 266608,
        "Letters": [
          "S",
          "M",
          "E",
          "T",
          "A",
          "N"
        ]
      },
      "37": {
        "SlotId": 37,
        "TermId": 126579,
        "Letters": [
          "S",
          "A",
          "K",
          "S"
        ]
      },
      "54": {
        "SlotId": 54,
        "TermId": 104287,
        "Letters": [
          "O",
          "K",
          "E",
          "R"
        ]
      },
      "50": {
        "SlotId": 50,
        "TermId": 7045,
        "Letters": [
          "R",
          "N",
          "A"
        ]
      },
      "61": {
        "SlotId": 61,
        "TermId": 43710,
        "Letters": [
          "S",
          "R",
          "N",
          "A"
        ]
      },
      "56": {
        "SlotId": 56,
        "TermId": 42634,
        "Letters": [
          "A",
          "N",
          "A"
        ]
      },
      "66": {
        "SlotId": 66,
        "TermId": 150964,
        "Letters": [
          "A",
          "A",
          "N"
        ]
      },
      "43": {
        "SlotId": 43,
        "TermId": 227865,
        "Letters": [
          "N",
          "E",
          "R",
          "A",
          "D",
          "N",
          "A"
        ]
      },
      "71": {
        "SlotId": 71,
        "TermId": 304041,
        "Letters": [
          "R",
          "O",
          "A",
          "D"
        ]
      },
      "80": {
        "SlotId": 80,
        "TermId": 9133,
        "Letters": [
          "N",
          "A"
        ]
      },
      "16": {
        "SlotId": 16,
        "TermId": 139514,
        "Letters": [
          "T",
          "R",
          "B",
          "U",
          "H"
        ]
      },
      "10": {
        "SlotId": 10,
        "TermId": 49202,
        "Letters": [
          "B",
          "A",
          "N",
          "A"
        ]
      },
      "12": {
        "SlotId": 12,
        "TermId": 6965,
        "Letters": [
          "H",
          "A"
        ]
      },
      "23": {
        "SlotId": 23,
        "TermId": 7312,
        "Letters": [
          "A",
          "L",
          "A"
        ]
      },
      "11": {
        "SlotId": 11,
        "TermId": 141709,
        "Letters": [
          "U",
          "L",
          "I",
          "C",
          "A"
        ]
      },
      "36": {
        "SlotId": 36,
        "TermId": 44171,
        "Letters": [
          "A",
          "C",
          "A"
        ]
      },
      "30": {
        "SlotId": 30,
        "TermId": 150949,
        "Letters": [
          "A",
          "A",
          "A"
        ]
      },
      "42": {
        "SlotId": 42,
        "TermId": 8071,
        "Letters": [
          "A",
          "A"
        ]
      },
      "119": {
        "SlotId": 119,
        "TermId": 151286,
        "Letters": [
          "C",
          "K",
          "A"
        ]
      },
      "103": {
        "SlotId": 103,
        "TermId": 150896,
        "Letters": [
          "A",
          "C",
          "A"
        ]
      },
      "115": {
        "SlotId": 115,
        "TermId": 3363,
        "Letters": [
          "C",
          "I"
        ]
      },
      "114": {
        "SlotId": 114,
        "TermId": 5811,
        "Letters": [
          "N",
          "O",
          "A"
        ]
      },
      "62": {
        "SlotId": 62,
        "TermId": 6776,
        "Letters": [
          "N",
          "O",
          "A"
        ]
      },
      "78": {
        "SlotId": 78,
        "TermId": 151728,
        "Letters": [
          "S",
          "A",
          "A"
        ]
      },
      "101": {
        "SlotId": 101,
        "TermId": 151208,
        "Letters": [
          "B",
          "O",
          "T"
        ]
      },
      "107": {
        "SlotId": 107,
        "TermId": 8046,
        "Letters": [
          "Č",
          "B"
        ]
      },
      "121": {
        "SlotId": 121,
        "TermId": 5924,
        "Letters": [
          "A",
          "T"
        ]
      },
      "84": {
        "SlotId": 84,
        "TermId": 241341,
        "Letters": [
          "P",
          "L",
          "A",
          "Č",
          "N",
          "A"
        ]
      },
      "94": {
        "SlotId": 94,
        "TermId": 7189,
        "Letters": [
          "L",
          "I",
          "N"
        ]
      },
      "89": {
        "SlotId": 89,
        "TermId": 252956,
        "Letters": [
          "P",
          "R",
          "LJ",
          "A",
          "N"
        ]
      },
      "77": {
        "SlotId": 77,
        "TermId": 278593,
        "Letters": [
          "U",
          "LJ",
          "N",
          "I"
        ]
      },
      "83": {
        "SlotId": 83,
        "TermId": 5882,
        "Letters": [
          "A",
          "U"
        ]
      },
      "70": {
        "SlotId": 70,
        "TermId": 34041,
        "Letters": [
          "T",
          "A",
          "R",
          "I"
        ]
      },
      "75": {
        "SlotId": 75,
        "TermId": 6899,
        "Letters": [
          "N",
          "T"
        ]
      },
      "58": {
        "SlotId": 58,
        "TermId": 7492,
        "Letters": [
          "S",
          "A",
          "N"
        ]
      },
      "100": {
        "SlotId": 100,
        "TermId": 8938,
        "Letters": [
          "I",
          "C"
        ]
      },
      "96": {
        "SlotId": 96,
        "TermId": 4162,
        "Letters": [
          "C",
          "M"
        ]
      },
      "108": {
        "SlotId": 108,
        "TermId": 92315,
        "Letters": [
          "M",
          "A",
          "T",
          "A"
        ]
      },
      "91": {
        "SlotId": 91,
        "TermId": 24077,
        "Letters": [
          "R",
          "A",
          "T",
          "I"
        ]
      },
      "74": {
        "SlotId": 74,
        "TermId": 47326,
        "Letters": [
          "A",
          "R",
          "H",
          "A",
          "I",
          "Č",
          "K",
          "I"
        ]
      },
      "92": {
        "SlotId": 92,
        "TermId": 8905,
        "Letters": [
          "H",
          "A"
        ]
      },
      "112": {
        "SlotId": 112,
        "TermId": 8045,
        "Letters": [
          "Č",
          "A"
        ]
      },
      "106": {
        "SlotId": 106,
        "TermId": 150950,
        "Letters": [
          "A",
          "A",
          "A"
        ]
      },
      "124": {
        "SlotId": 124,
        "TermId": 307305,
        "Letters": [
          "I",
          "A"
        ]
      },
      "87": {
        "SlotId": 87,
        "TermId": 43362,
        "Letters": [
          "S",
          "A",
          "R",
          "A"
        ]
      },
      "82": {
        "SlotId": 82,
        "TermId": 150965,
        "Letters": [
          "A",
          "A",
          "N"
        ]
      },
      "97": {
        "SlotId": 97,
        "TermId": 5825,
        "Letters": [
          "A",
          "M",
          "A",
          "N"
        ]
      },
      "93": {
        "SlotId": 93,
        "TermId": 9123,
        "Letters": [
          "M",
          "T"
        ]
      },
      "104": {
        "SlotId": 104,
        "TermId": 31823,
        "Letters": [
          "S",
          "U",
          "T",
          "I"
        ]
      },
      "81": {
        "SlotId": 81,
        "TermId": 129393,
        "Letters": [
          "S",
          "K",
          "A",
          "U",
          "T"
        ]
      },
      "110": {
        "SlotId": 110,
        "TermId": 150975,
        "Letters": [
          "A",
          "A",
          "T"
        ]
      },
      "98": {
        "SlotId": 98,
        "TermId": 144,
        "Letters": [
          "S",
          "A",
          "A",
          "B"
        ]
      },
      "123": {
        "SlotId": 123,
        "TermId": 30381,
        "Letters": [
          "S",
          "L",
          "A",
          "B",
          "I"
        ]
      },
      "105": {
        "SlotId": 105,
        "TermId": 46002,
        "Letters": [
          "A",
          "N",
          "A"
        ]
      },
      "117": {
        "SlotId": 117,
        "TermId": 151099,
        "Letters": [
          "A",
          "N",
          "A"
        ]
      },
      "111": {
        "SlotId": 111,
        "TermId": 5769,
        "Letters": [
          "A",
          "L"
        ]
      },
      "90": {
        "SlotId": 90,
        "TermId": 106255,
        "Letters": [
          "O",
          "S",
          "N",
          "A",
          "K"
        ]
      },
      "72": {
        "SlotId": 72,
        "TermId": 264967,
        "Letters": [
          "S",
          "I",
          "S",
          "N",
          "A"
        ]
      },
      "102": {
        "SlotId": 102,
        "TermId": 153944,
        "Letters": [
          "A",
          "N",
          "A"
        ]
      },
      "79": {
        "SlotId": 79,
        "TermId": 205106,
        "Letters": [
          "L",
          "O",
          "Ž",
          "N",
          "A"
        ]
      },
      "95": {
        "SlotId": 95,
        "TermId": 276706,
        "Letters": [
          "T",
          "R",
          "Ž",
          "N",
          "A"
        ]
      },
      "65": {
        "SlotId": 65,
        "TermId": 73793,
        "Letters": [
          "I",
          "D",
          "E",
          "N",
          "T"
        ]
      },
      "85": {
        "SlotId": 85,
        "TermId": 63690,
        "Letters": [
          "E",
          "L",
          "L",
          "I",
          "S"
        ]
      },
      "55": {
        "SlotId": 55,
        "TermId": 273933,
        "Letters": [
          "T",
          "E",
          "R",
          "A",
          "S",
          "N",
          "A"
        ]
      },
      "59": {
        "SlotId": 59,
        "TermId": 9060,
        "Letters": [
          "L",
          "T"
        ]
      },
      "41": {
        "SlotId": 41,
        "TermId": 4817,
        "Letters": [
          "M",
          "D",
          "L",
          "V"
        ]
      },
      "64": {
        "SlotId": 64,
        "TermId": 310,
        "Letters": [
          "N",
          "E",
          "V",
          "E",
          "N"
        ]
      },
      "52": {
        "SlotId": 52,
        "TermId": 102501,
        "Letters": [
          "O",
          "B",
          "A",
          "D"
        ]
      },
      "48": {
        "SlotId": 48,
        "TermId": 49929,
        "Letters": [
          "B",
          "E",
          "N",
          "Z",
          "I",
          "L"
        ]
      },
      "76": {
        "SlotId": 76,
        "TermId": 73768,
        "Letters": [
          "I",
          "D",
          "I"
        ]
      },
      "69": {
        "SlotId": 69,
        "TermId": 48608,
        "Letters": [
          "A",
          "V",
          "I",
          "Z",
          "O"
        ]
      },
      "60": {
        "SlotId": 60,
        "TermId": 8816,
        "Letters": [
          "E",
          "O"
        ]
      },
      "33": {
        "SlotId": 33,
        "TermId": 131968,
        "Letters": [
          "S",
          "R",
          "O",
          "K"
        ]
      },
      "45": {
        "SlotId": 45,
        "TermId": 7406,
        "Letters": [
          "P",
          "A",
          "R"
        ]
      },
      "27": {
        "SlotId": 27,
        "TermId": 220855,
        "Letters": [
          "N",
          "A",
          "P",
          "A",
          "R",
          "N",
          "A"
        ]
      },
      "57": {
        "SlotId": 57,
        "TermId": 55363,
        "Letters": [
          "C",
          "R",
          "P",
          "K",
          "E"
        ]
      },
      "53": {
        "SlotId": 53,
        "TermId": 19385,
        "Letters": [
          "P",
          "O",
          "V",
          "I"
        ]
      },
      "63": {
        "SlotId": 63,
        "TermId": 266012,
        "Letters": [
          "S",
          "L",
          "N",
          "O"
        ]
      },
      "46": {
        "SlotId": 46,
        "TermId": 6448,
        "Letters": [
          "B",
          "C",
          "L"
        ]
      },
      "51": {
        "SlotId": 51,
        "TermId": 6374,
        "Letters": [
          "A",
          "B",
          "A"
        ]
      }
    },
    "UsedTermsIds": [
      138971,
      307501,
      88397,
      6391,
      7262,
      7815,
      7762,
      6988,
      7766,
      7770,
      7270,
      3362,
      5965,
      7774,
      150632,
      150751,
      150805,
      150812,
      150820,
      306940,
      307043,
      6957,
      7273,
      8025,
      6990,
      7817,
      26017,
      94454,
      7192,
      90769,
      8471,
      150962,
      79679,
      102231,
      151103,
      132219,
      5968,
      157768,
      139877,
      150961,
      150888,
      8936,
      150966,
      6757,
      266608,
      126579,
      104287,
      7045,
      43710,
      42634,
      150964,
      227865,
      304041,
      9133,
      139514,
      49202,
      6965,
      7312,
      141709,
      44171,
      150949,
      8071,
      151286,
      150896,
      3363,
      5811,
      6776,
      151728,
      151208,
      8046,
      5924,
      241341,
      7189,
      252956,
      278593,
      5882,
      34041,
      6899,
      7492,
      8938,
      4162,
      92315,
      24077,
      47326,
      8905,
      8045,
      150950,
      307305,
      43362,
      150965,
      5825,
      9123,
      31823,
      129393,
      150975,
      144,
      30381,
      46002,
      151099,
      5769,
      106255,
      264967,
      153944,
      205106,
      276706,
      73793,
      63690,
      273933,
      9060,
      4817,
      310,
      102501,
      49929,
      73768,
      48608,
      8816,
      131968,
      7406,
      220855,
      55363,
      19385,
      266012,
      6448,
      6374
    ],
    "LettersByCell": {
      "1_10": "T",
      "2_10": "O",
      "3_10": "R",
      "4_10": "O",
      "5_10": "N",
      "6_10": "T",
      "7_10": "O",
      "1_4": "O",
      "2_4": "T",
      "3_4": "T",
      "4_4": "A",
      "5_4": "W",
      "6_4": "A",
      "5_2": "L",
      "5_3": "A",
      "5_5": "S",
      "5_6": "O",
      "5_7": "N",
      "2_9": "A",
      "1_2": "I",
      "1_8": "A",
      "1_11": "R",
      "2_1": "A",
      "3_11": "A",
      "4_6": "N",
      "6_1": "C",
      "7_1": "A",
      "6_14": "A",
      "10_11": "A",
      "10_1": "A",
      "10_14": "A",
      "13_4": "A",
      "13_10": "A",
      "15_1": "A",
      "17_3": "A",
      "17_12": "C",
      "18_4": "C",
      "18_5": "A",
      "18_7": "S",
      "18_11": "I",
      "3_12": "N",
      "3_13": "I",
      "1_1": "M",
      "1_3": "M",
      "2_3": "S",
      "3_1": "C",
      "4_1": "K",
      "3_2": "A",
      "4_2": "A",
      "4_3": "N",
      "6_7": "S",
      "7_7": "A",
      "5_9": "A",
      "5_11": "S",
      "2_5": "A",
      "2_6": "R",
      "2_7": "A",
      "3_5": "R",
      "1_6": "A",
      "3_6": "I",
      "3_7": "K",
      "3_8": "I",
      "1_7": "A",
      "4_8": "A",
      "4_9": "A",
      "6_9": "E",
      "6_8": "M",
      "6_11": "A",
      "6_12": "N",
      "7_11": "K",
      "8_11": "S",
      "7_12": "E",
      "7_13": "R",
      "8_13": "N",
      "9_13": "A",
      "8_12": "R",
      "8_14": "A",
      "9_14": "N",
      "9_12": "A",
      "10_12": "D",
      "11_12": "N",
      "12_12": "A",
      "10_9": "R",
      "10_10": "O",
      "11_13": "A",
      "1_12": "B",
      "1_13": "U",
      "1_14": "H",
      "2_12": "A",
      "4_12": "A",
      "2_14": "A",
      "2_13": "L",
      "4_13": "C",
      "5_13": "A",
      "4_14": "A",
      "5_14": "A",
      "17_13": "K",
      "17_14": "A",
      "16_5": "A",
      "17_5": "C",
      "17_6": "I",
      "17_1": "N",
      "17_2": "O",
      "9_10": "N",
      "11_10": "A",
      "11_8": "S",
      "11_9": "A",
      "16_2": "B",
      "18_2": "T",
      "16_1": "Č",
      "18_1": "A",
      "13_1": "P",
      "14_1": "L",
      "14_2": "I",
      "14_3": "N",
      "13_2": "R",
      "13_3": "LJ",
      "13_5": "N",
      "12_3": "U",
      "15_3": "I",
      "12_2": "A",
      "11_2": "T",
      "11_1": "N",
      "9_1": "S",
      "15_4": "C",
      "16_4": "M",
      "16_6": "T",
      "16_7": "A",
      "14_6": "R",
      "15_6": "A",
      "12_13": "R",
      "13_13": "H",
      "14_13": "A",
      "15_13": "I",
      "16_13": "Č",
      "18_13": "I",
      "13_14": "A",
      "16_14": "A",
      "18_14": "A",
      "12_11": "S",
      "12_14": "A",
      "14_14": "N",
      "14_11": "A",
      "14_12": "M",
      "15_12": "T",
      "15_10": "S",
      "15_11": "U",
      "13_11": "K",
      "16_11": "T",
      "16_9": "A",
      "16_10": "A",
      "17_10": "A",
      "18_10": "B",
      "18_8": "L",
      "18_9": "A",
      "17_9": "N",
      "17_8": "A",
      "13_7": "O",
      "13_8": "S",
      "13_9": "N",
      "12_8": "I",
      "14_8": "N",
      "15_8": "A",
      "15_7": "N",
      "12_7": "L",
      "14_7": "Ž",
      "14_5": "T",
      "14_9": "A",
      "10_5": "I",
      "11_5": "D",
      "12_5": "E",
      "12_6": "L",
      "12_9": "S",
      "8_9": "T",
      "9_9": "E",
      "8_8": "L",
      "7_8": "D",
      "9_8": "V",
      "9_6": "N",
      "9_7": "E",
      "7_5": "O",
      "7_6": "B",
      "8_6": "E",
      "10_6": "Z",
      "11_6": "I",
      "11_4": "I",
      "10_3": "A",
      "10_4": "V",
      "10_7": "O",
      "6_5": "R",
      "8_5": "K",
      "6_3": "P",
      "7_3": "A",
      "8_3": "R",
      "9_3": "N",
      "8_2": "C",
      "8_4": "P",
      "9_4": "O",
      "9_2": "L",
      "7_2": "B"
    }
  }
}